auto_paper-0.1.0.dist-info/METADATA
auto_paper-0.1.0.dist-info/WHEEL
auto_paper.py
auto_paper-0.1.0.dist-info/RECORD
