Metadata-Version: 2.1
Name: auto-paper
Version: 0.1.0
Author-Email: Nasy <nasyxx+git@gmail.com>
License: MIT
Requires-Python: >=3.10
Requires-Dist: arxiv>=1.4.3
Requires-Dist: tyro>=0.4.2
Requires-Dist: httpx>=0.23.3
